BiMLPA/__init__.py
BiMLPA/bimlpa.py
BiMLPA/community.py
BiMLPA/generator.py
BiMLPA/modularity.py
BiMLPA/utils.py
bimlpa-0.1.2.dist-info/LICENSE
bimlpa-0.1.2.dist-info/METADATA
bimlpa-0.1.2.dist-info/WHEEL
bimlpa-0.1.2.dist-info/top_level.txt
bimlpa-0.1.2.dist-info/RECORD
